{
  "item": [
    {
      "id": "dd375389-b374-405b-8617-eeb7cb29c7b8",
      "name": "Entitlements",
      "description": {
        "content": "Vendor entitlement queries from Synopsys Cloud.",
        "type": "text/plain"
      },
      "item": [
        {
          "id": "7fbcc1f1-6120-4d3c-9b0c-17e63fe3ae66",
          "name": "Get Vendor Entitlements",
          "request": {
            "name": "Get Vendor Entitlements",
            "description": {
              "content": "Called by Synopsys Cloud to retrieve available licenses for a specific customer. This endpoint is registered by the vendor during onboarding. Returns an array of entitlements with associated license details.",
              "type": "text/plain"
            },
            "url": {
              "path": [
                "entitlements"
              ],
              "host": [
                "{{baseUrl}}"
              ],
              "query": [],
              "variable": []
            },
            "header": [
              {
                "key": "Content-Type",
                "value": "application/json"
              },
              {
                "key": "Accept",
                "value": "application/json"
              }
            ],
            "method": "POST",
            "auth": null,
            "body": {
              "mode": "raw",
              "raw": "{\n  \"customerId\": \"<string>\",\n  \"productId\": \"<string>\",\n  \"requestId\": \"<string>\"\n}",
              "options": {
                "raw": {
                  "language": "json"
                }
              }
            }
          },
          "response": [
            {
              "id": "ca562df2-b5ee-4359-ac01-c1ed62d4883d",
              "name": "Entitlements returned",
              "originalRequest": {
                "url": {
                  "path": [
                    "entitlements"
                  ],
                  "host": [
                    "{{baseUrl}}"
                  ],
                  "query": [],
                  "variable": []
                },
                "header": [
                  {
                    "description": {
                      "content": "Added as a part of security scheme: apikey",
                      "type": "text/plain"
                    },
                    "key": "X-API-Key",
                    "value": "<API Key>"
                  },
                  {
                    "key": "Accept",
                    "value": "application/json"
                  }
                ],
                "method": "POST",
                "body": {
                  "mode": "raw",
                  "raw": "{\n  \"customerId\": \"<string>\",\n  \"productId\": \"<string>\",\n  \"requestId\": \"<string>\"\n}",
                  "options": {
                    "raw": {
                      "language": "json"
                    }
                  }
                }
              },
              "status": "OK",
              "code": 200,
              "header": [
                {
                  "key": "Content-Type",
                  "value": "application/json"
                }
              ],
              "body": "{\n  \"customerId\": \"string\",\n  \"entitlements\": [\n    {\n      \"entitlementId\": \"string\",\n      \"productId\": \"string\",\n      \"productName\": \"string\",\n      \"quantity\": 7159,\n      \"expiresAt\": \"2013-08-11T17:55:20.948Z\",\n      \"licenseRequestApi\": \"string\"\n    },\n    {\n      \"entitlementId\": \"string\",\n      \"productId\": \"string\",\n      \"productName\": \"string\",\n      \"quantity\": 5273,\n      \"expiresAt\": \"1990-11-14T06:20:31.015Z\",\n      \"licenseRequestApi\": \"string\"\n    }\n  ]\n}",
              "cookie": [],
              "_postman_previewlanguage": "json"
            },
            {
              "id": "617bb28e-5ed7-4a37-bf71-bb12b2fe11c7",
              "name": "Bad request",
              "originalRequest": {
                "url": {
                  "path": [
                    "entitlements"
                  ],
                  "host": [
                    "{{baseUrl}}"
                  ],
                  "query": [],
                  "variable": []
                },
                "header": [
                  {
                    "description": {
                      "content": "Added as a part of security scheme: apikey",
                      "type": "text/plain"
                    },
                    "key": "X-API-Key",
                    "value": "<API Key>"
                  },
                  {
                    "key": "Accept",
                    "value": "application/json"
                  }
                ],
                "method": "POST",
                "body": {
                  "mode": "raw",
                  "raw": "{\n  \"customerId\": \"<string>\",\n  \"productId\": \"<string>\",\n  \"requestId\": \"<string>\"\n}",
                  "options": {
                    "raw": {
                      "language": "json"
                    }
                  }
                }
              },
              "status": "Bad Request",
              "code": 400,
              "header": [
                {
                  "key": "Content-Type",
                  "value": "application/json"
                }
              ],
              "body": "{\n  \"code\": \"string\",\n  \"message\": \"string\",\n  \"statusCode\": 7716,\n  \"tid\": \"string\"\n}",
              "cookie": [],
              "_postman_previewlanguage": "json"
            },
            {
              "id": "eec4dd57-9c11-4b10-b5ef-d90de629a56d",
              "name": "Unauthorized",
              "originalRequest": {
                "url": {
                  "path": [
                    "entitlements"
                  ],
                  "host": [
                    "{{baseUrl}}"
                  ],
                  "query": [],
                  "variable": []
                },
                "header": [
                  {
                    "description": {
                      "content": "Added as a part of security scheme: apikey",
                      "type": "text/plain"
                    },
                    "key": "X-API-Key",
                    "value": "<API Key>"
                  }
                ],
                "method": "POST",
                "body": {
                  "mode": "raw",
                  "raw": "{\n  \"customerId\": \"<string>\",\n  \"productId\": \"<string>\",\n  \"requestId\": \"<string>\"\n}",
                  "options": {
                    "raw": {
                      "language": "json"
                    }
                  }
                }
              },
              "status": "Unauthorized",
              "code": 401,
              "header": [
                {
                  "key": "Content-Type",
                  "value": "text/plain"
                }
              ],
              "body": "",
              "cookie": [],
              "_postman_previewlanguage": "text"
            }
          ],
          "event": [],
          "protocolProfileBehavior": {
            "disableBodyPruning": true
          }
        }
      ],
      "event": []
    },
    {
      "id": "f9d31c88-8611-4a62-9db7-dcbaf308ee7f",
      "name": "Licenses",
      "description": {
        "content": "License file generation and delivery.",
        "type": "text/plain"
      },
      "item": [
        {
          "id": "0a36163d-c3f1-483c-a903-7afd94d1d1b4",
          "name": "Generate License File",
          "request": {
            "name": "Generate License File",
            "description": {
              "content": "Called by Synopsys Cloud to generate and retrieve a license file for a customer. This endpoint is dynamically provided via the entitlement response. Supports synchronous delivery (within 20 seconds) and asynchronous delivery with polling.",
              "type": "text/plain"
            },
            "url": {
              "path": [
                "licenses"
              ],
              "host": [
                "{{baseUrl}}"
              ],
              "query": [],
              "variable": []
            },
            "header": [
              {
                "key": "Content-Type",
                "value": "application/json"
              },
              {
                "key": "Accept",
                "value": "application/json"
              }
            ],
            "method": "POST",
            "auth": null,
            "body": {
              "mode": "raw",
              "raw": "{\n  \"entitlementId\": \"<string>\",\n  \"customerId\": \"<string>\",\n  \"hostId\": \"<string>\",\n  \"quantity\": \"<integer>\"\n}",
              "options": {
                "raw": {
                  "language": "json"
                }
              }
            }
          },
          "response": [
            {
              "id": "880c6879-d7ef-452d-8d72-56d709cf11b5",
              "name": "License generated",
              "originalRequest": {
                "url": {
                  "path": [
                    "licenses"
                  ],
                  "host": [
                    "{{baseUrl}}"
                  ],
                  "query": [],
                  "variable": []
                },
                "header": [
                  {
                    "description": {
                      "content": "Added as a part of security scheme: apikey",
                      "type": "text/plain"
                    },
                    "key": "X-API-Key",
                    "value": "<API Key>"
                  },
                  {
                    "key": "Accept",
                    "value": "application/json"
                  }
                ],
                "method": "POST",
                "body": {
                  "mode": "raw",
                  "raw": "{\n  \"entitlementId\": \"<string>\",\n  \"customerId\": \"<string>\",\n  \"hostId\": \"<string>\",\n  \"quantity\": \"<integer>\"\n}",
                  "options": {
                    "raw": {
                      "language": "json"
                    }
                  }
                }
              },
              "status": "OK",
              "code": 200,
              "header": [
                {
                  "key": "Content-Type",
                  "value": "application/json"
                }
              ],
              "body": "{\n  \"licenseId\": \"string\",\n  \"downloadType\": \"Async\",\n  \"licenseData\": \"string\",\n  \"expiresAt\": \"1983-02-02T02:09:50.281Z\"\n}",
              "cookie": [],
              "_postman_previewlanguage": "json"
            },
            {
              "id": "8ee497d6-3c90-41a2-95c5-9860cbd7ef4f",
              "name": "Asynchronous license generation initiated",
              "originalRequest": {
                "url": {
                  "path": [
                    "licenses"
                  ],
                  "host": [
                    "{{baseUrl}}"
                  ],
                  "query": [],
                  "variable": []
                },
                "header": [
                  {
                    "description": {
                      "content": "Added as a part of security scheme: apikey",
                      "type": "text/plain"
                    },
                    "key": "X-API-Key",
                    "value": "<API Key>"
                  },
                  {
                    "key": "Accept",
                    "value": "application/json"
                  }
                ],
                "method": "POST",
                "body": {
                  "mode": "raw",
                  "raw": "{\n  \"entitlementId\": \"<string>\",\n  \"customerId\": \"<string>\",\n  \"hostId\": \"<string>\",\n  \"quantity\": \"<integer>\"\n}",
                  "options": {
                    "raw": {
                      "language": "json"
                    }
                  }
                }
              },
              "status": "Accepted",
              "code": 202,
              "header": [
                {
                  "key": "Content-Type",
                  "value": "application/json"
                }
              ],
              "body": "{\n  \"licenseId\": \"string\",\n  \"downloadType\": \"Async\",\n  \"pollStartDateTime\": \"2007-02-14T08:26:54.588Z\",\n  \"pollIntervalSec\": 6113,\n  \"downloadApi\": {\n    \"url\": \"string\"\n  }\n}",
              "cookie": [],
              "_postman_previewlanguage": "json"
            },
            {
              "id": "cadb2725-04f4-40c3-8c4b-3f269452b897",
              "name": "Bad request",
              "originalRequest": {
                "url": {
                  "path": [
                    "licenses"
                  ],
                  "host": [
                    "{{baseUrl}}"
                  ],
                  "query": [],
                  "variable": []
                },
                "header": [
                  {
                    "description": {
                      "content": "Added as a part of security scheme: apikey",
                      "type": "text/plain"
                    },
                    "key": "X-API-Key",
                    "value": "<API Key>"
                  },
                  {
                    "key": "Accept",
                    "value": "application/json"
                  }
                ],
                "method": "POST",
                "body": {
                  "mode": "raw",
                  "raw": "{\n  \"entitlementId\": \"<string>\",\n  \"customerId\": \"<string>\",\n  \"hostId\": \"<string>\",\n  \"quantity\": \"<integer>\"\n}",
                  "options": {
                    "raw": {
                      "language": "json"
                    }
                  }
                }
              },
              "status": "Bad Request",
              "code": 400,
              "header": [
                {
                  "key": "Content-Type",
                  "value": "application/json"
                }
              ],
              "body": "{\n  \"code\": \"string\",\n  \"message\": \"string\",\n  \"statusCode\": 7716,\n  \"tid\": \"string\"\n}",
              "cookie": [],
              "_postman_previewlanguage": "json"
            }
          ],
          "event": [],
          "protocolProfileBehavior": {
            "disableBodyPruning": true
          }
        },
        {
          "id": "170fa5ee-d491-443c-aadd-729c1e52b19b",
          "name": "Download License File",
          "request": {
            "name": "Download License File",
            "description": {
              "content": "Retrieves a previously generated license file by its identifier. Used for asynchronous license polling scenarios.",
              "type": "text/plain"
            },
            "url": {
              "path": [
                "licenses",
                ":licenseId"
              ],
              "host": [
                "{{baseUrl}}"
              ],
              "query": [],
              "variable": [
                {
                  "disabled": false,
                  "type": "any",
                  "value": "<string>",
                  "key": "licenseId",
                  "description": "(Required) License file identifier."
                }
              ]
            },
            "header": [
              {
                "key": "Accept",
                "value": "application/json"
              }
            ],
            "method": "GET",
            "auth": null
          },
          "response": [
            {
              "id": "a0d2a3bd-477a-47ef-aced-84138c252b2a",
              "name": "License file content returned",
              "originalRequest": {
                "url": {
                  "path": [
                    "licenses",
                    ":licenseId"
                  ],
                  "host": [
                    "{{baseUrl}}"
                  ],
                  "query": [],
                  "variable": [
                    {
                      "disabled": false,
                      "type": "any",
                      "value": "<string>",
                      "key": "licenseId",
                      "description": "(Required) License file identifier."
                    }
                  ]
                },
                "header": [
                  {
                    "description": {
                      "content": "Added as a part of security scheme: apikey",
                      "type": "text/plain"
                    },
                    "key": "X-API-Key",
                    "value": "<API Key>"
                  },
                  {
                    "key": "Accept",
                    "value": "application/json"
                  }
                ],
                "method": "GET",
                "body": {}
              },
              "status": "OK",
              "code": 200,
              "header": [
                {
                  "key": "Content-Type",
                  "value": "application/json"
                }
              ],
              "body": "{\n  \"licenseId\": \"string\",\n  \"downloadType\": \"Async\",\n  \"licenseData\": \"string\",\n  \"expiresAt\": \"1983-02-02T02:09:50.281Z\"\n}",
              "cookie": [],
              "_postman_previewlanguage": "json"
            },
            {
              "id": "b00d8a1b-ec62-40a4-b721-76defcb17f38",
              "name": "License not yet ready",
              "originalRequest": {
                "url": {
                  "path": [
                    "licenses",
                    ":licenseId"
                  ],
                  "host": [
                    "{{baseUrl}}"
                  ],
                  "query": [],
                  "variable": [
                    {
                      "disabled": false,
                      "type": "any",
                      "value": "<string>",
                      "key": "licenseId",
                      "description": "(Required) License file identifier."
                    }
                  ]
                },
                "header": [
                  {
                    "description": {
                      "content": "Added as a part of security scheme: apikey",
                      "type": "text/plain"
                    },
                    "key": "X-API-Key",
                    "value": "<API Key>"
                  }
                ],
                "method": "GET",
                "body": {}
              },
              "status": "Accepted",
              "code": 202,
              "header": [
                {
                  "key": "Content-Type",
                  "value": "text/plain"
                }
              ],
              "body": "",
              "cookie": [],
              "_postman_previewlanguage": "text"
            },
            {
              "id": "82682bcd-2b65-444c-bbaf-8d5fc33f293d",
              "name": "License not found",
              "originalRequest": {
                "url": {
                  "path": [
                    "licenses",
                    ":licenseId"
                  ],
                  "host": [
                    "{{baseUrl}}"
                  ],
                  "query": [],
                  "variable": [
                    {
                      "disabled": false,
                      "type": "any",
                      "value": "<string>",
                      "key": "licenseId",
                      "description": "(Required) License file identifier."
                    }
                  ]
                },
                "header": [
                  {
                    "description": {
                      "content": "Added as a part of security scheme: apikey",
                      "type": "text/plain"
                    },
                    "key": "X-API-Key",
                    "value": "<API Key>"
                  }
                ],
                "method": "GET",
                "body": {}
              },
              "status": "Not Found",
              "code": 404,
              "header": [
                {
                  "key": "Content-Type",
                  "value": "text/plain"
                }
              ],
              "body": "",
              "cookie": [],
              "_postman_previewlanguage": "text"
            }
          ],
          "event": [],
          "protocolProfileBehavior": {
            "disableBodyPruning": true
          }
        }
      ],
      "event": []
    }
  ],
  "event": [],
  "variable": [
    {
      "type": "string",
      "value": "https://api.synopsys.com/openlink/v1",
      "key": "baseUrl"
    }
  ],
  "auth": {
    "type": "apikey",
    "apikey": [
      {
        "key": "key",
        "value": "X-API-Key"
      },
      {
        "key": "value",
        "value": "{{apiKey}}"
      },
      {
        "key": "in",
        "value": "header"
      }
    ]
  },
  "info": {
    "_postman_id": "ae7f937e-2b80-43e8-8497-dcfa043ad24b",
    "name": "Synopsys Cloud OpenLink API",
    "schema": "https://schema.getpostman.com/json/collection/v2.1.0/collection.json",
    "description": {
      "content": "The Synopsys Cloud OpenLink API enables semiconductor vendors to interoperate with Synopsys Cloud for managing product entitlements and license distribution. Vendors register endpoints during onboarding and respond to license queries from Synopsys Cloud. The API supports both synchronous and asynchronous license file delivery.",
      "type": "text/plain"
    }
  }
}